[
    {
        "id": 16,
        "nome": "tyeste1 11111",
        "data_compra": "2023-02-01",
        "valor_compra": 3333.33,
        "vida_util": 2,
        "categoria": "Eletrônico",
        "status": "Disponível",
        "foto": "WhatsApp Image 2025-01-18 at 09.35.54.jpeg",
        "garantia_data": "2024-02-01",
        "garantia_meses": 12,
        "custo_manutencao": 0,
        "custo_total": 3333.33
    },
    {
        "id": 17,
        "nome": "tyeste1 11111",
        "data_compra": "2023-02-01",
        "valor_compra": 3333.33,
        "vida_util": 2,
        "categoria": "Eletrônico",
        "status": "Disponível",
        "foto": "WhatsApp Image 2025-01-18 at 09.35.54.jpeg",
        "garantia_data": "2024-02-01",
        "garantia_meses": 12,
        "custo_manutencao": 0,
        "custo_total": 3333.33
    },
    {
        "id": 18,
        "nome": "tyeste1 11111",
        "data_compra": "2023-02-01",
        "valor_compra": 3333.33,
        "vida_util": 2,
        "categoria": "Eletrônico",
        "status": "Disponível",
        "foto": "WhatsApp Image 2025-01-18 at 09.35.54.jpeg",
        "garantia_data": "2024-02-01",
        "garantia_meses": 12,
        "custo_manutencao": 0,
        "custo_total": 3333.33
    },
    {
        "id": 19,
        "nome": "tyeste1 11111",
        "data_compra": "2023-02-01",
        "valor_compra": 3333.33,
        "vida_util": 2,
        "categoria": "Eletrônico",
        "status": "Disponível",
        "foto": "WhatsApp Image 2025-01-18 at 09.35.54.jpeg",
        "garantia_data": "2024-02-01",
        "garantia_meses": 12,
        "custo_manutencao": 0,
        "custo_total": 3333.33
    },
    {
        "id": 20,
        "nome": "tyeste1 11111",
        "data_compra": "2023-02-01",
        "valor_compra": 3333.33,
        "vida_util": 2,
        "categoria": "Eletrônico",
        "status": "Disponível",
        "foto": "WhatsApp Image 2025-01-18 at 09.35.54.jpeg",
        "garantia_data": "2024-02-01",
        "garantia_meses": 12,
        "custo_manutencao": 0,
        "custo_total": 3333.33
    },
    {
        "id": 22,
        "nome": "tyeste1 11111",
        "data_compra": "2023-02-01",
        "valor_compra": 3333.33,
        "vida_util": 2,
        "categoria": "Eletrônico",
        "status": "Disponível",
        "foto": "WhatsApp Image 2025-01-18 at 09.35.54.jpeg",
        "garantia_data": "2024-02-01",
        "garantia_meses": 12,
        "custo_manutencao": 0,
        "custo_total": 3333.33
    },
    {
        "id": 23,
        "nome": "tyeste1 11111",
        "data_compra": "2023-02-01",
        "valor_compra": 3333.33,
        "vida_util": 2,
        "categoria": "Eletrônico",
        "status": "Disponível",
        "foto": "WhatsApp Image 2025-01-18 at 09.35.54.jpeg",
        "garantia_data": "2024-02-01",
        "garantia_meses": 12,
        "custo_manutencao": 0,
        "custo_total": 3333.33
    },
    {
        "id": 24,
        "nome": "tyeste1 11111",
        "data_compra": "2023-02-01",
        "valor_compra": 3333.33,
        "vida_util": 2,
        "categoria": "Eletrônico",
        "status": "Disponível",
        "foto": "WhatsApp Image 2025-01-18 at 09.35.54.jpeg",
        "garantia_data": "2024-02-01",
        "garantia_meses": 12,
        "custo_manutencao": 0,
        "custo_total": 3333.33
    },
    {
        "id": 25,
        "nome": "tyeste1 11111",
        "data_compra": "2023-02-01",
        "valor_compra": 333333.0,
        "vida_util": 2,
        "categoria": "Eletrônico",
        "status": "Disponível",
        "foto": "WhatsApp Image 2025-01-18 at 09.35.54.jpeg",
        "garantia_data": "2031-05-01",
        "garantia_meses": 99,
        "custo_manutencao": 0.0,
        "custo_total": 333333.0
    },
    {
        "id": 26,
        "nome": "tyeste1 11111",
        "data_compra": "2023-02-01",
        "valor_compra": 3333.33,
        "vida_util": 2,
        "categoria": "Eletrônico",
        "status": "Disponível",
        "foto": "WhatsApp Image 2025-01-18 at 09.35.54.jpeg",
        "garantia_data": "2024-02-01",
        "garantia_meses": 12,
        "custo_manutencao": 0,
        "custo_total": 3333.33
    },
    {
        "id": 11,
        "nome": "dsasdasd",
        "data_compra": "2023-01-01",
        "valor_compra": 1111.0,
        "vida_util": 2,
        "categoria": "adsasdasd",
        "status": "Disponível",
        "foto": null,
        "garantia_data": "2025-01-01",
        "garantia_meses": 24,
        "custo_manutencao": 1110.0,
        "custo_total": 2221.0
    }
]